horkos_doc/__init__.py
horkos_doc/_cmdline.py
horkos_doc/_definitions.py
horkos_doc/_renderer.py
horkos_doc/_site_generator.py
horkos_doc/templates/base.html
horkos_doc/templates/dataset.html
horkos_doc/templates/expand_script.js
horkos_doc/templates/footer.html
horkos_doc/templates/links.html
horkos_doc/templates/listing.html
horkos_doc/templates/navbar.html
horkos_doc/templates/raw_json.json
horkos_doc/templates/search.html
horkos_doc/templates/style.css
tests/__init__.py
tests/test_cmdline.py
tests/test_renderer.py
horkos_doc-0.0.10.dist-info/METADATA
horkos_doc-0.0.10.dist-info/WHEEL
horkos_doc-0.0.10.dist-info/entry_points.txt
horkos_doc-0.0.10.dist-info/top_level.txt
horkos_doc-0.0.10.dist-info/RECORD
