Metadata-Version: 2.1
Name: horkos-doc
Version: 0.0.10
Summary: A library for building data documentation.
Home-page: https://gitlab.com/kjschiroo/horkos-doc
Author: Kevin Schiroo
Author-email: kjschiroo@gmail.com
License: MIT
Platform: UNKNOWN
Classifier: Programming Language :: Python :: 3
Classifier: License :: OSI Approved :: MIT License
Requires-Python: >=3.7
Requires-Dist: beautifulsoup4
Requires-Dist: bleach
Requires-Dist: jinja2
Requires-Dist: markdown
Requires-Dist: horkos
